openai_decorator/__init__.py
openai_decorator/main.py
openai_decorator-0.1.3.dist-info/LICENSE
openai_decorator-0.1.3.dist-info/METADATA
openai_decorator-0.1.3.dist-info/WHEEL
openai_decorator-0.1.3.dist-info/entry_points.txt
openai_decorator-0.1.3.dist-info/RECORD
