Metadata-Version: 2.1
Name: openai-decorator
Version: 0.1.3
Summary: This package allows you to genrate function paramater values by integrating OpenAI's API function capabilities through signature and docstring analysis.
Home-page: https://github.com/shruti222patel/openai-decorator
License: MIT
Keywords: openai,decorator,functions,openai-functions,openai-decorator,openai-api,openai-api-functions,openai-api-decorator,openai
Author: Shruti Patel
Author-email: shruti222patel@gmail.com
Requires-Python: >=3.8,<4.0
Classifier: Intended Audience :: Developers
Classifier: License :: OSI Approved :: MIT License
Classifier: Operating System :: OS Independent
Classifier: Programming Language :: Python :: 3
Classifier: Programming Language :: Python :: 3.8
Classifier: Programming Language :: Python :: 3.9
Classifier: Programming Language :: Python :: 3.10
Classifier: Programming Language :: Python :: 3.11
Classifier: Topic :: Software Development :: Libraries :: Python Modules
Requires-Dist: docstring-parser (>=0.15,<0.16)
Requires-Dist: openai (>=0.27.8,<0.28.0)
Requires-Dist: requests (>=2.31.0,<3.0.0)
Requires-Dist: tenacity (>=8.2.2,<9.0.0)
Project-URL: Repository, https://github.com/shruti222patel/openai-decorator
